ase_notebook/__init__.py
ase_notebook/atom_info.py
ase_notebook/atoms_convert.py
ase_notebook/attr_doc.py
ase_notebook/color.py
ase_notebook/configuration.py
ase_notebook/draw_elements.py
ase_notebook/draw_utils.py
ase_notebook/viewer.py
ase_notebook/backend/__init__.py
ase_notebook/backend/gui.py
ase_notebook/backend/svg.py
ase_notebook/backend/threejs.py
ase_notebook/data/__init__.py
ase_notebook/data/example_pyrite.atoms.json
ase_notebook/data/vesta_element_data.json
ase_notebook/data/__pycache__/__init__.cpython-36.pyc
ase_notebook-0.3.2.dist-info/LICENSE
ase_notebook-0.3.2.dist-info/METADATA
ase_notebook-0.3.2.dist-info/WHEEL
ase_notebook-0.3.2.dist-info/entry_points.txt
ase_notebook-0.3.2.dist-info/top_level.txt
ase_notebook-0.3.2.dist-info/RECORD
