Metadata-Version: 2.1
Name: ase-notebook
Version: 0.3.2
Summary: Highly configurable 2D (SVG) & 3D (threejs) visualisations for ASE/Pymatgen structures, within the Jupyter Notebook
Home-page: https://github.com/chrisjsewell/ase-notebook
Author: Chris Sewell
Author-email: chrisj_sewell@hotmail.com
Maintainer: Chris Sewell
Maintainer-email: chrisj_sewell@hotmail.com
License: MIT
Project-URL: Documentation, https://ase-notebook.readthedocs.io/
Platform: UNKNOWN
Classifier: Development Status :: 4 - Beta
Classifier: Programming Language :: Python
Classifier: Programming Language :: Python :: 3
Classifier: Programming Language :: Python :: 3.5
Classifier: Programming Language :: Python :: 3.6
Classifier: Programming Language :: Python :: 3.7
Classifier: Programming Language :: Python :: Implementation :: CPython
Classifier: Operating System :: OS Independent
Classifier: License :: OSI Approved :: BSD License
Classifier: Topic :: Scientific/Engineering :: Chemistry
Classifier: Topic :: Scientific/Engineering :: Physics
Requires-Python: >=3.5
Requires-Dist: ase (<4,>=3.18)
Requires-Dist: attrs (<20,>=19)
Requires-Dist: importlib-resources (<2,>=1)
Requires-Dist: numpy (<1.19,>=1.16.4)
Requires-Dist: matplotlib (<4,>=3.1)
Requires-Dist: svgwrite (<2,>=1.3)
Provides-Extra: code_style
Requires-Dist: black (==19.3b0) ; extra == 'code_style'
Requires-Dist: pre-commit (==1.17.0) ; extra == 'code_style'
Requires-Dist: flake8 (<3.8.0,>=3.7.0) ; extra == 'code_style'
Requires-Dist: doc8 (<0.9.0,>=0.8.0) ; extra == 'code_style'
Requires-Dist: pygments ; extra == 'code_style'
Provides-Extra: docs
Requires-Dist: sphinx (<3,>=1.8) ; extra == 'docs'
Requires-Dist: sphinx-rtd-theme ; extra == 'docs'
Requires-Dist: ipypublish (>=0.10.10) ; extra == 'docs'
Requires-Dist: ipython ; extra == 'docs'
Provides-Extra: flake8_plugins
Requires-Dist: flake8-comprehensions ; extra == 'flake8_plugins'
Requires-Dist: flake8-docstrings ; extra == 'flake8_plugins'
Requires-Dist: flake8-builtins ; extra == 'flake8_plugins'
Requires-Dist: import-order ; extra == 'flake8_plugins'
Provides-Extra: svg2pdf
Requires-Dist: svglib (<1,>=0.9) ; extra == 'svg2pdf'
Requires-Dist: reportlab (<4,>=3.5) ; extra == 'svg2pdf'
Provides-Extra: svgconcat
Requires-Dist: svgutils (<0.4,>=0.3) ; extra == 'svgconcat'
Provides-Extra: testing
Requires-Dist: coverage ; extra == 'testing'
Requires-Dist: pytest (<4,>=3.6) ; extra == 'testing'
Requires-Dist: pytest-cov ; extra == 'testing'
Provides-Extra: threejs
Requires-Dist: pythreejs (<3,>=2.1) ; extra == 'threejs'
Requires-Dist: ipywidgets (<8,>=7.5) ; extra == 'threejs'
